alien/__init__.py
alien/alien.py
alien/alien_invasion.py
alien/bullet.py
alien/button.py
alien/game_fuctions.py
alien/game_stats.py
alien/scoreboard.py
alien/settings.py
alien/ship.py
alien/font/freesansbold.ttf
alien/image/alien.bmp
alien/image/ship.bmp
alienGame-1.1.0.dist-info/METADATA
alienGame-1.1.0.dist-info/WHEEL
alienGame-1.1.0.dist-info/top_level.txt
alienGame-1.1.0.dist-info/RECORD
